celery_mutex/__init__.py
celery_mutex-0.1.0.dist-info/DESCRIPTION.rst
celery_mutex-0.1.0.dist-info/METADATA
celery_mutex-0.1.0.dist-info/pydist.json
celery_mutex-0.1.0.dist-info/RECORD
celery_mutex-0.1.0.dist-info/top_level.txt
celery_mutex-0.1.0.dist-info/WHEEL
