Metadata-Version: 2.0
Name: celery-mutex
Version: 0.1.0
Summary: Mutex for Celery tasks, which can be refined.
Home-page: https://github.com/brolewis/celery_mutex
Author: Lewis Franklin
Author-email: lewis.franklin@gmail.com
License: BSD License
Keywords: Celery tasks mutex
Platform: any
Classifier: License :: OSI Approved :: BSD License
Classifier: Intended Audience :: Developers
Classifier: Development Status :: 3 - Alpha
Classifier: Programming Language :: Python
Classifier: Programming Language :: Python :: 2
Classifier: Operating System :: OS Independent
Classifier: Topic :: Software Development :: Libraries :: Python Modules
Classifier: Topic :: System :: Distributed Computing
Requires-Dist: kazoo (>=1.0)
